{
   "sportplace":{
      "contact":{
         "name":"Krkavec",
         "address":"Krkavec, Ledce, 330 14",
         "phone":"",
         "email":"",
         "url":"",
         "lat":49.8031866,
         "lon":13.3393209,
         "z":16.5
      },
      "open":{
         "monday":[0, 24],
         "tuesday":[0, 24],
         "wednesday":[0, 24],
         "thursday":[0, 24],
         "friday":[0, 24],
         "saturday":[0, 24],
         "sunday":[0, 24]
      },
      "sport":[
         {
            "cyklistika":{
               "price":0,
               "outside":true,
               "reservation":false
            }
         },
         {
            "beh":{
               "price":0,
               "outside":true,
               "reservation":false
            }
         }
      ]
   }
}
